mkdocs_author_plugin/__init__.py
mkdocs_author_plugin/plugin.py
mkdocs_author_plugin-0.1.0.dist-info/LICENSE
mkdocs_author_plugin-0.1.0.dist-info/METADATA
mkdocs_author_plugin-0.1.0.dist-info/WHEEL
mkdocs_author_plugin-0.1.0.dist-info/entry_points.txt
mkdocs_author_plugin-0.1.0.dist-info/top_level.txt
mkdocs_author_plugin-0.1.0.dist-info/RECORD
